<stg><name>Crypto_Pipeline_VITIS_LOOP_126_5</name>


<trans_list>

<trans id="38" from="1" to="2">
<condition id="-1">
<or_exp><and_exp></and_exp></or_exp>
</condition>
</trans>

<trans id="35" from="2" to="3">
<condition id="-1">
<or_exp><and_exp></and_exp></or_exp>
</condition>
</trans>
</trans_list>



<state_list>

<state id="1" st_id="2">

<operation id="6" st_id="1" stage="1" lat="1">
<core>NULL</core>
<MemPortIdVec></MemPortIdVec>
<condition id="-1">
<or_exp><and_exp></and_exp></or_exp>
</condition>

<Node id="4" bw="13" op_0_bw="32">
<![CDATA[
newFuncRoot:0 %i = alloca i32 1

]]></Node>
<StgValue><ssdm name="i"/></StgValue>
</operation>

<operation id="7" st_id="1" stage="1" lat="1">
<core>NULL</core>
<MemPortIdVec></MemPortIdVec>
<condition id="-1">
<or_exp><and_exp></and_exp></or_exp>
</condition>

<Node id="5" bw="13" op_0_bw="13" op_1_bw="13">
<![CDATA[
newFuncRoot:1 %zext_ln14_5_read = read i13 @_ssdm_op_Read.ap_auto.i13, i13 %zext_ln14_5

]]></Node>
<StgValue><ssdm name="zext_ln14_5_read"/></StgValue>
</operation>

<operation id="8" st_id="1" stage="1" lat="1">
<core>NULL</core>
<MemPortIdVec></MemPortIdVec>
<condition id="-1">
<or_exp><and_exp></and_exp></or_exp>
</condition>

<Node id="6" bw="0" op_0_bw="13" op_1_bw="13">
<![CDATA[
newFuncRoot:2 %store_ln0 = store i13 0, i13 %i

]]></Node>
<StgValue><ssdm name="store_ln0"/></StgValue>
</operation>

<operation id="9" st_id="1" stage="1" lat="1">
<core>NULL</core>
<MemPortIdVec></MemPortIdVec>
<condition id="-1">
<or_exp><and_exp></and_exp></or_exp>
</condition>

<Node id="7" bw="0" op_0_bw="0">
<![CDATA[
newFuncRoot:3 %br_ln0 = br void %VITIS_LOOP_127_6

]]></Node>
<StgValue><ssdm name="br_ln0"/></StgValue>
</operation>

<operation id="10" st_id="1" stage="1" lat="1">
<core>NULL</core>
<MemPortIdVec></MemPortIdVec>
<condition id="-1">
<or_exp><and_exp></and_exp></or_exp>
</condition>

<Node id="9" bw="13" op_0_bw="13" op_1_bw="0">
<![CDATA[
VITIS_LOOP_127_6:0 %i_7 = load i13 %i

]]></Node>
<StgValue><ssdm name="i_7"/></StgValue>
</operation>

<operation id="11" st_id="1" stage="1" lat="1">
<core>NULL</core>
<MemPortIdVec></MemPortIdVec>
<condition id="-1">
<or_exp><and_exp></and_exp></or_exp>
</condition>

<Node id="10" bw="0" op_0_bw="0" op_1_bw="32" op_2_bw="32" op_3_bw="32" op_4_bw="32" op_5_bw="0">
<![CDATA[
VITIS_LOOP_127_6:1 %specpipeline_ln0 = specpipeline void @_ssdm_op_SpecPipeline, i32 4294967295, i32 0, i32 1, i32 0, void @p_str

]]></Node>
<StgValue><ssdm name="specpipeline_ln0"/></StgValue>
</operation>

<operation id="12" st_id="1" stage="1" lat="1">
<core>Cmp</core>
<MemPortIdVec></MemPortIdVec>
<condition id="-1">
<or_exp><and_exp></and_exp></or_exp>
</condition>

<Node id="11" bw="1" op_0_bw="13" op_1_bw="13">
<![CDATA[
VITIS_LOOP_127_6:2 %icmp_ln126 = icmp_eq  i13 %i_7, i13 4096

]]></Node>
<StgValue><ssdm name="icmp_ln126"/></StgValue>
</operation>

<operation id="13" st_id="1" stage="1" lat="1">
<core>Adder</core>
<MemPortIdVec></MemPortIdVec>
<condition id="-1">
<or_exp><and_exp></and_exp></or_exp>
</condition>

<Node id="12" bw="13" op_0_bw="13" op_1_bw="13">
<![CDATA[
VITIS_LOOP_127_6:3 %add_ln126 = add i13 %i_7, i13 1

]]></Node>
<StgValue><ssdm name="add_ln126"/></StgValue>
</operation>

<operation id="14" st_id="1" stage="1" lat="1">
<core>NULL</core>
<MemPortIdVec></MemPortIdVec>
<condition id="-1">
<or_exp><and_exp></and_exp></or_exp>
</condition>

<Node id="13" bw="0" op_0_bw="1" op_1_bw="0" op_2_bw="0">
<![CDATA[
VITIS_LOOP_127_6:4 %br_ln126 = br i1 %icmp_ln126, void %VITIS_LOOP_127_6.split, void %sw.epilog.loopexit2.exitStub

]]></Node>
<StgValue><ssdm name="br_ln126"/></StgValue>
</operation>

<operation id="15" st_id="1" stage="1" lat="1">
<core>NULL</core>
<MemPortIdVec></MemPortIdVec>
<condition id="-1">
<or_exp><and_exp><literal name="icmp_ln126" val="0"/>
</and_exp></or_exp>
</condition>

<Node id="15" bw="64" op_0_bw="13">
<![CDATA[
VITIS_LOOP_127_6.split:0 %i_7_cast = zext i13 %i_7

]]></Node>
<StgValue><ssdm name="i_7_cast"/></StgValue>
</operation>

<operation id="16" st_id="1" stage="1" lat="1">
<core>Adder</core>
<MemPortIdVec></MemPortIdVec>
<condition id="-1">
<or_exp><and_exp><literal name="icmp_ln126" val="0"/>
</and_exp></or_exp>
</condition>

<Node id="16" bw="13" op_0_bw="13" op_1_bw="13">
<![CDATA[
VITIS_LOOP_127_6.split:1 %add_ln8 = add i13 %zext_ln14_5_read, i13 %i_7

]]></Node>
<StgValue><ssdm name="add_ln8"/></StgValue>
</operation>

<operation id="17" st_id="1" stage="1" lat="1">
<core>NULL</core>
<MemPortIdVec></MemPortIdVec>
<condition id="-1">
<or_exp><and_exp><literal name="icmp_ln126" val="0"/>
</and_exp></or_exp>
</condition>

<Node id="21" bw="12" op_0_bw="32" op_1_bw="64" op_2_bw="64">
<![CDATA[
VITIS_LOOP_127_6.split:6 %DataTemp_addr = getelementptr i32 %DataTemp, i64 0, i64 %i_7_cast

]]></Node>
<StgValue><ssdm name="DataTemp_addr"/></StgValue>
</operation>

<operation id="18" st_id="1" stage="2" lat="2">
<core>RAM</core>
<MemPortIdVec></MemPortIdVec>
<condition id="-1">
<or_exp><and_exp><literal name="icmp_ln126" val="0"/>
</and_exp></or_exp>
</condition>

<Node id="22" bw="32" op_0_bw="12">
<![CDATA[
VITIS_LOOP_127_6.split:7 %DataTemp_load = load i12 %DataTemp_addr

]]></Node>
<StgValue><ssdm name="DataTemp_load"/></StgValue>
</operation>

<operation id="19" st_id="1" stage="1" lat="1">
<core>NULL</core>
<MemPortIdVec></MemPortIdVec>
<condition id="-1">
<or_exp><and_exp><literal name="icmp_ln126" val="0"/>
</and_exp></or_exp>
</condition>

<Node id="24" bw="0" op_0_bw="13" op_1_bw="13" op_2_bw="0" op_3_bw="0">
<![CDATA[
VITIS_LOOP_127_6.split:9 %store_ln126 = store i13 %add_ln126, i13 %i

]]></Node>
<StgValue><ssdm name="store_ln126"/></StgValue>
</operation>
</state>

<state id="2" st_id="3">

<operation id="20" st_id="2" stage="1" lat="2">
<core>RAM</core>
<MemPortIdVec></MemPortIdVec>
<condition id="-1">
<or_exp><and_exp></and_exp></or_exp>
</condition>

<Node id="22" bw="32" op_0_bw="12">
<![CDATA[
VITIS_LOOP_127_6.split:7 %DataTemp_load = load i12 %DataTemp_addr

]]></Node>
<StgValue><ssdm name="DataTemp_load"/></StgValue>
</operation>

<operation id="27" st_id="2" stage="1" lat="1">
<core>NULL</core>
<MemPortIdVec></MemPortIdVec>
<condition id="-1">
<or_exp><and_exp><literal name="icmp_ln126" val="1"/>
</and_exp></or_exp>
</condition>

<Node id="27" bw="0">
<![CDATA[
sw.epilog.loopexit2.exitStub:0 %ret_ln0 = ret

]]></Node>
<StgValue><ssdm name="ret_ln0"/></StgValue>
</operation>
</state>

<state id="3" st_id="4">

<operation id="21" st_id="3" stage="1" lat="1">
<core>NULL</core>
<MemPortIdVec></MemPortIdVec>
<condition id="-1">
<or_exp><and_exp></and_exp></or_exp>
</condition>

<Node id="17" bw="64" op_0_bw="13">
<![CDATA[
VITIS_LOOP_127_6.split:2 %zext_ln8 = zext i13 %add_ln8

]]></Node>
<StgValue><ssdm name="zext_ln8"/></StgValue>
</operation>

<operation id="22" st_id="3" stage="1" lat="1">
<core>NULL</core>
<MemPortIdVec></MemPortIdVec>
<condition id="-1">
<or_exp><and_exp></and_exp></or_exp>
</condition>

<Node id="18" bw="13" op_0_bw="32" op_1_bw="64" op_2_bw="64">
<![CDATA[
VITIS_LOOP_127_6.split:3 %data_ram_0_addr = getelementptr i32 %data_ram_0, i64 0, i64 %zext_ln8

]]></Node>
<StgValue><ssdm name="data_ram_0_addr"/></StgValue>
</operation>

<operation id="23" st_id="3" stage="1" lat="1">
<core>NULL</core>
<MemPortIdVec></MemPortIdVec>
<condition id="-1">
<or_exp><and_exp></and_exp></or_exp>
</condition>

<Node id="19" bw="0" op_0_bw="0" op_1_bw="64" op_2_bw="64" op_3_bw="64">
<![CDATA[
VITIS_LOOP_127_6.split:4 %speclooptripcount_ln126 = speclooptripcount void @_ssdm_op_SpecLoopTripCount, i64 4096, i64 4096, i64 4096

]]></Node>
<StgValue><ssdm name="speclooptripcount_ln126"/></StgValue>
</operation>

<operation id="24" st_id="3" stage="1" lat="1">
<core>NULL</core>
<MemPortIdVec></MemPortIdVec>
<condition id="-1">
<or_exp><and_exp></and_exp></or_exp>
</condition>

<Node id="20" bw="0" op_0_bw="0" op_1_bw="0">
<![CDATA[
VITIS_LOOP_127_6.split:5 %specloopname_ln126 = specloopname void @_ssdm_op_SpecLoopName, void @empty_13

]]></Node>
<StgValue><ssdm name="specloopname_ln126"/></StgValue>
</operation>

<operation id="25" st_id="3" stage="1" lat="1">
<core>RAM</core>
<MemPortIdVec></MemPortIdVec>
<condition id="-1">
<or_exp><and_exp></and_exp></or_exp>
</condition>

<Node id="23" bw="0" op_0_bw="32" op_1_bw="13">
<![CDATA[
VITIS_LOOP_127_6.split:8 %store_ln8 = store i32 %DataTemp_load, i13 %data_ram_0_addr

]]></Node>
<StgValue><ssdm name="store_ln8"/></StgValue>
</operation>

<operation id="26" st_id="3" stage="1" lat="1">
<core>NULL</core>
<MemPortIdVec></MemPortIdVec>
<condition id="-1">
<or_exp><and_exp></and_exp></or_exp>
</condition>

<Node id="25" bw="0" op_0_bw="0">
<![CDATA[
VITIS_LOOP_127_6.split:10 %br_ln126 = br void %VITIS_LOOP_127_6

]]></Node>
<StgValue><ssdm name="br_ln126"/></StgValue>
</operation>
</state>
</state_list>


<ports>
</ports>


<dataflows>
</dataflows>


</stg>
